author_rank/__init__.py
author_rank/graph.py
author_rank/score.py
author_rank/tmp.py
author_rank/utils.py
author_rank-0.1.3.dist-info/LICENSE.txt
author_rank-0.1.3.dist-info/METADATA
author_rank-0.1.3.dist-info/WHEEL
author_rank-0.1.3.dist-info/top_level.txt
author_rank-0.1.3.dist-info/RECORD
