Metadata-Version: 2.1
Name: author-rank
Version: 0.1.3
Summary: UNKNOWN
Home-page: https://github.com/adidier17/AuthorRank
Author: Valentino Constantinou, Annie Didier
Author-email: akdidier@jpl.caltech.edu
License: MIT
Download-URL: https://github.com/adidier17/AuthorRank/archive/0.1.3.tar.gz
Keywords: author_rank,PageRank,network,graph,edges,nodes,authorship,AuthorRank
Platform: UNKNOWN
License-File: LICENSE.txt
Requires-Dist: networkx
Requires-Dist: python-utils
Requires-Dist: scipy
